cgm/__init__.py
cgm/_utils.py
cgm/core.py
cgm/example_graphs.py
cgm/py.typed
cgm/inference/__init__.py
cgm/inference/belief_propagation.py
cgm/inference/forward_sampling.py
cgm/inference/variable_elimination.py
docs/conf.py
tests/__init__.py
tests/test_core.py
tests/test_inference.py
cgm-0.0.10.dist-info/LICENSE
cgm-0.0.10.dist-info/METADATA
cgm-0.0.10.dist-info/WHEEL
cgm-0.0.10.dist-info/top_level.txt
cgm-0.0.10.dist-info/RECORD
