Metadata-Version: 2.1
Name: cgm
Version: 0.0.10
Summary: Causal Graphical Models
Author-email: Kyle Ellefsen <kyleellefsen@gmail.com>
License: MIT License
Project-URL: Source, https://github.com/kyleellefsen/cgm
Project-URL: PyPi, https://pypi.org/project/cgm/
Project-URL: Issues, https://github.com/kyleellefsen/cgm/issues
Keywords: cgm,pgm,dag,causal inference,factors
Classifier: Development Status :: 3 - Alpha
Classifier: Intended Audience :: Developers
Classifier: Topic :: Software Development :: Build Tools
Classifier: License :: OSI Approved :: MIT License
Classifier: Programming Language :: Python :: 3 :: Only
Requires-Python: >=3.8
License-File: LICENSE
Requires-Dist: numpy
Provides-Extra: docs
Requires-Dist: sphinx-rtd-theme ; extra == 'docs'
Requires-Dist: myst-parser ; extra == 'docs'
Requires-Dist: sphinx-math-dollar ; extra == 'docs'
Requires-Dist: sphinx-autodoc2 ; extra == 'docs'
Requires-Dist: sphinx-copybutton ; extra == 'docs'
Requires-Dist: sphinxcontrib.mermaid ; extra == 'docs'
Requires-Dist: sphinx-tabs ; extra == 'docs'
